pypi_cli/__init__.py
pypi_cli/__main__.py
pypi_command_line-1.7.1.dist-info/LICENSE
pypi_command_line-1.7.1.dist-info/METADATA
pypi_command_line-1.7.1.dist-info/WHEEL
pypi_command_line-1.7.1.dist-info/entry_points.txt
pypi_command_line-1.7.1.dist-info/top_level.txt
pypi_command_line-1.7.1.dist-info/RECORD
