Metadata-Version: 2.1
Name: pypi-command-line
Version: 1.7.1
Summary: A beautiful command line interface for the Python Package Index
Home-page: https://wasi-master.github.io/pypi-command-line/
Author: Wasi Master
Author-email: arianmollik323@gmail.com
License: MIT
Project-URL: Bug Tracker, https://github.com/wasi-master/pypi-command-line/issues
Project-URL: Source, https://github.com/wasi-master/pypi-command-line
Project-URL: Documentation, https://wasi-master.github.io/pypi-command-line
Project-URL: Say Thanks, https://saythanks.io/to/wasi-master
Keywords: pypi,cli,pypi cli,pypi-cli,pypi command line,pypi-command-line,command line,command-line,pypi command line interface,pypi-command-line-interface,command line interface,command-line-interface,pypi command line application,pypi-command-line-application,command line application,command-line-application,command line interface,command-line-interface,command line application,command-line-application
Classifier: Development Status :: 5 - Production/Stable
Classifier: Environment :: Console
Classifier: Intended Audience :: Developers
Classifier: Intended Audience :: End Users/Desktop
Classifier: License :: OSI Approved :: MIT License
Classifier: Natural Language :: English
Classifier: Operating System :: OS Independent
Classifier: Programming Language :: Python :: 3
Classifier: Programming Language :: Python :: 3 :: Only
Classifier: Programming Language :: Python :: 3.6
Classifier: Programming Language :: Python :: 3.7
Classifier: Programming Language :: Python :: 3.8
Classifier: Programming Language :: Python :: 3.9
Classifier: Programming Language :: Python :: 3.10
Classifier: Topic :: Terminals
Requires-Python: >=3.6
License-File: LICENSE
Requires-Dist: bs4
Requires-Dist: rich-click
Requires-Dist: humanize
Requires-Dist: packaging
Requires-Dist: questionary
Requires-Dist: requests
Requires-Dist: rich
Requires-Dist: rich-rst
Requires-Dist: thefuzz
Requires-Dist: typer
Requires-Dist: wheel-filename
Provides-Extra: speedups
Requires-Dist: lxml ; extra == 'speedups'
Requires-Dist: rapidfuzz ; extra == 'speedups'
Requires-Dist: requests-cache ; extra == 'speedups'
Requires-Dist: shellingham ; extra == 'speedups'
Requires-Dist: ujson ; extra == 'speedups'
